mypythonlib_nasim_project/__init__.py
mypythonlib_nasim_project/clean_text.py
mypythonlib_nasim_project/config.py
mypythonlib_nasim_project/ent_ait_fix.py
mypythonlib_nasim_project/fix_lines.py
mypythonlib_nasim_project/liaisons.py
mypythonlib_nasim_project/main.py
mypythonlib_nasim_project/name_correction.py
mypythonlib_nasim_project/remove_pnum_hilight_title.py
mypythonlib_nasim_project/replace_numbers.py
mypythonlib_nasim_project/replace_special_chars.py
mypythonlib_nasim_project/replace_words.py
mypythonlib_nasim_project/split_chapters.py
mypythonlib_nasim_project-0.3.5.dist-info/METADATA
mypythonlib_nasim_project-0.3.5.dist-info/WHEEL
mypythonlib_nasim_project-0.3.5.dist-info/top_level.txt
mypythonlib_nasim_project-0.3.5.dist-info/RECORD
