Metadata-Version: 2.1
Name: mypythonlib_nasim_project
Version: 0.3.5
Summary: Atlas Cleaning Text Project
Author: Me
